integration_tests/__init__.py
redis_lua/__init__.py
redis_lua/exceptions.py
redis_lua/regions.py
redis_lua/render.py
redis_lua/script.py
redis_lua/testing.py
redis_lua-2.0.8.dist-info/DESCRIPTION.rst
redis_lua-2.0.8.dist-info/METADATA
redis_lua-2.0.8.dist-info/RECORD
redis_lua-2.0.8.dist-info/WHEEL
redis_lua-2.0.8.dist-info/metadata.json
redis_lua-2.0.8.dist-info/top_level.txt
