Metadata-Version: 2.0
Name: redis-lua
Version: 2.0.8
Summary: A set of tools to ease LUA scripting when dealing with Redis.
Home-page: UNKNOWN
Author: Julien Kauffmann
Author-email: julien.kauffmann@freelan.org
License: UNKNOWN
Platform: UNKNOWN
Classifier: Intended Audience :: Developers
Classifier: Operating System :: OS Independent
Classifier: Programming Language :: Python :: 2
Classifier: Programming Language :: Python :: 2.7
Classifier: Programming Language :: Python :: 3
Classifier: Programming Language :: Python :: 3.3
Classifier: Programming Language :: Python :: 3.4
Classifier: Programming Language :: Python :: 3.5
Classifier: Topic :: Software Development
Classifier: Topic :: Software Development :: Libraries :: Python Modules
Classifier: Development Status :: 5 - Production/Stable
Requires-Dist: redis (>=2.10.3)
Requires-Dist: six (>=1.10.0,<2.0.0)
